{
    "count": 1,
    "entities": [
        {
            "uuid": "6fb6ee8f-7b8b-436e-930f-13c9b03cfee4",
            "properties": {
                "name": "Sanjay Sharma",
                "identifier": {
                    "entity_def_id": "contact",
                    "uuid": "6fb6ee8f-7b8b-436e-930f-13c9b03cfee4",
                    "value": "Sanjay Sharma"
                },
                "linkedin": "sanjayrsharma",
                "job_levels": [
                    "l_100_individual",
                    "l_500_exec"
                ],
                "job_departments": [
                    "management"
                ]
            },
            "related_entities": {
                "contact_item.has_contact_item.forward": {
                    "entities": [
                        {
                            "uuid": "12d38baf-c084-4163-b523-7615b9806aa1",
                            "related_uuid": "6fb6ee8f-7b8b-436e-930f-13c9b03cfee4",
                            "properties": {
                                "job_title": "Chairman & CEO"
                            }
                        }
                    ]
                }
            }
        }
    ]
}