{
    "count": 1,
    "entities": [
        {
            "uuid": "c0f8f7ec-74da-4d46-b2e4-0585536c7ce9",
            "properties": {
                "name": "Sam Gutmann",
                "identifier": {
                    "entity_def_id": "contact",
                    "uuid": "c0f8f7ec-74da-4d46-b2e4-0585536c7ce9",
                    "value": "Sam Gutmann"
                },
                "linkedin": "samgutmann",
                "job_levels": [
                    "l_500_exec"
                ],
                "job_departments": [
                    "management"
                ]
            },
            "related_entities": {
                "contact_item.has_contact_item.forward": {
                    "entities": [
                        {
                            "uuid": "eafd478c-14ed-4502-a539-bc914f988873",
                            "related_uuid": "c0f8f7ec-74da-4d46-b2e4-0585536c7ce9",
                            "properties": {
                                "job_title": "CEO"
                            }
                        }
                    ]
                }
            }
        }
    ]
}