{
    "count": 1,
    "entities": [
        {
            "uuid": "1ced53c6-8920-4101-8874-10ca1b5a095e",
            "properties": {
                "name": "Sachin More",
                "identifier": {
                    "entity_def_id": "contact",
                    "uuid": "1ced53c6-8920-4101-8874-10ca1b5a095e",
                    "value": "Sachin More"
                },
                "linkedin": "sachin-more-6558b030",
                "job_levels": [
                    "l_300_director"
                ],
                "job_departments": [
                    "finance",
                    "medical_science"
                ]
            },
            "related_entities": {
                "contact_item.has_contact_item.forward": {
                    "entities": [
                        {
                            "uuid": "48a52878-5618-466f-8cec-8fb2e3737611",
                            "related_uuid": "1ced53c6-8920-4101-8874-10ca1b5a095e",
                            "properties": {
                                "job_title": "Director, Trust-Compliance & Business Operations"
                            }
                        }
                    ]
                }
            }
        }
    ]
}