{
    "count": 15,
    "entities": [
        {
            "identifier": {
                "entity_def_id": "job_title",
                "permalink": "ceo",
                "uuid": "55161575-f3e0-3dfb-a114-5c5d63d67d29",
                "value": "CEO"
            }
        },
        {
            "identifier": {
                "entity_def_id": "job_title",
                "permalink": "consultant",
                "uuid": "7adfa4f2-ba93-33e6-81e0-24de375434b0",
                "value": "Consultant"
            }
        },
        {
            "identifier": {
                "entity_def_id": "job_title",
                "permalink": "co-founder",
                "uuid": "67f94724-6ebb-36e8-ba2a-600d3fda1e4f",
                "value": "Co-Founder"
            }
        },
        {
            "identifier": {
                "entity_def_id": "job_title",
                "permalink": "cfo",
                "uuid": "12d872a3-607f-3925-9a8b-73df02dbbfbd",
                "value": "CFO"
            }
        },
        {
            "identifier": {
                "entity_def_id": "job_title",
                "permalink": "cto",
                "uuid": "1244eff5-7249-3271-bf8d-c5692f7cbaf0",
                "value": "CTO"
            }
        },
        {
            "identifier": {
                "entity_def_id": "job_title",
                "permalink": "cmo",
                "uuid": "99330263-c899-3a05-8dc1-8add519cae39",
                "value": "CMO"
            }
        },
        {
            "identifier": {
                "entity_def_id": "job_title",
                "permalink": "community-manager",
                "uuid": "bfd38a01-1f3e-3508-b609-b080c7f669d0",
                "value": "Community Manager"
            }
        },
        {
            "identifier": {
                "entity_def_id": "job_title",
                "permalink": "customer-success-manager",
                "uuid": "dad7007f-e4e7-31d2-bf75-69c4f1990e75",
                "value": "Customer Success Manager"
            }
        },
        {
            "identifier": {
                "entity_def_id": "job_title",
                "permalink": "manager-customer-success",
                "uuid": "b8afc7ac-06e2-351a-b93a-6df46f017f0c",
                "value": "Manager, Customer Success"
            }
        },
        {
            "identifier": {
                "entity_def_id": "job_title",
                "permalink": "cro",
                "uuid": "5922bcca-31a5-347d-a587-ac39e8b7c1e4",
                "value": "CRO"
            }
        },
        {
            "identifier": {
                "entity_def_id": "job_title",
                "permalink": "cpo",
                "uuid": "d4cf9c5d-657b-3fb1-b2c2-33fdb19ac2ff",
                "value": "CPO"
            }
        },
        {
            "identifier": {
                "entity_def_id": "job_title",
                "permalink": "cgo",
                "uuid": "63e64fb7-f6bf-3edd-a708-e1b75126a6fb",
                "value": "CGO"
            }
        },
        {
            "identifier": {
                "entity_def_id": "job_title",
                "permalink": "senior-director-customer-success",
                "uuid": "4c710ec4-8b24-3a87-9209-c5a5697bbc9a",
                "value": "Senior Director, Customer Success"
            }
        },
        {
            "identifier": {
                "entity_def_id": "job_title",
                "permalink": "consultant-customer-success",
                "uuid": "ed93cc45-d35b-3ec7-8994-a14be6e64a01",
                "value": "Consultant, Customer Success"
            }
        },
        {
            "identifier": {
                "entity_def_id": "job_title",
                "permalink": "senior-engineer-customer-success",
                "uuid": "85d97278-fe71-3c8a-b90e-f756b10eb58f",
                "value": "Senior Engineer, Customer Success"
            }
        }
    ]
}