{
    "count": 17,
    "entities": [
        {
            "identifier": {
                "entity_def_id": "job_title",
                "permalink": "ceo",
                "uuid": "55161575-f3e0-3dfb-a114-5c5d63d67d29",
                "value": "CEO"
            }
        },
        {
            "identifier": {
                "entity_def_id": "job_title",
                "permalink": "consultant",
                "uuid": "7adfa4f2-ba93-33e6-81e0-24de375434b0",
                "value": "Consultant"
            }
        },
        {
            "identifier": {
                "entity_def_id": "job_title",
                "permalink": "cfo",
                "uuid": "12d872a3-607f-3925-9a8b-73df02dbbfbd",
                "value": "CFO"
            }
        },
        {
            "identifier": {
                "entity_def_id": "job_title",
                "permalink": "controller",
                "uuid": "594c103f-2c6e-34c3-98ab-059f031e0c1a",
                "value": "Controller"
            }
        },
        {
            "identifier": {
                "entity_def_id": "job_title",
                "permalink": "senior-consultant",
                "uuid": "c32664aa-9318-3dbe-9476-b1439c92abca",
                "value": "Senior Consultant"
            }
        },
        {
            "identifier": {
                "entity_def_id": "job_title",
                "permalink": "director-communications",
                "uuid": "05163693-1ed8-3f4c-8623-320e5f7f194e",
                "value": "Director, Communications"
            }
        },
        {
            "identifier": {
                "entity_def_id": "job_title",
                "permalink": "customer-success-manager",
                "uuid": "dad7007f-e4e7-31d2-bf75-69c4f1990e75",
                "value": "Customer Success Manager"
            }
        },
        {
            "identifier": {
                "entity_def_id": "job_title",
                "permalink": "chief-engineer",
                "uuid": "574c0251-3fc3-3e91-91f1-38a199a4d606",
                "value": "Chief Engineer"
            }
        },
        {
            "identifier": {
                "entity_def_id": "job_title",
                "permalink": "financial-controller",
                "uuid": "3d450b59-616f-3a3a-aadf-c3b7cf292fc1",
                "value": "Financial Controller"
            }
        },
        {
            "identifier": {
                "entity_def_id": "job_title",
                "permalink": "office-coordinator",
                "uuid": "818f037d-c546-35b1-8d3b-86cec9714e15",
                "value": "Office Coordinator"
            }
        },
        {
            "identifier": {
                "entity_def_id": "job_title",
                "permalink": "director-customer-success",
                "uuid": "cb271bcc-8723-321b-910b-47abf4992bed",
                "value": "Director, Customer Success"
            }
        },
        {
            "identifier": {
                "entity_def_id": "job_title",
                "permalink": "chief-people-officer",
                "uuid": "787bf94f-69bd-3055-bb9f-361e6b23c0c2",
                "value": "Chief People Officer"
            }
        },
        {
            "identifier": {
                "entity_def_id": "job_title",
                "permalink": "campaign-manager",
                "uuid": "def43a61-3ba9-3806-ad36-d71701cdeb1c",
                "value": "Campaign Manager"
            }
        },
        {
            "identifier": {
                "entity_def_id": "job_title",
                "permalink": "chief-development-officer",
                "uuid": "fd36e010-9f82-318c-b1a2-37fc8b3af31f",
                "value": "Chief Development Officer"
            }
        },
        {
            "identifier": {
                "entity_def_id": "job_title",
                "permalink": "product-consultant",
                "uuid": "3284d4db-43c4-34fa-b2d3-3f9c999fac84",
                "value": "Product Consultant"
            }
        },
        {
            "identifier": {
                "entity_def_id": "job_title",
                "permalink": "collection-analyst",
                "uuid": "b60c41fc-831a-3d44-9f1d-afc73e9fe0b8",
                "value": "Collection Analyst"
            }
        },
        {
            "identifier": {
                "entity_def_id": "job_title",
                "permalink": "chief-development-officer-engineering",
                "uuid": "bb595ba9-f045-3a88-b4a0-97b82d46374c",
                "value": "Chief Development Officer, Engineering"
            }
        }
    ]
}